baseui/__init__.py
baseui/components/__init__.py
baseui/components/rounded_button.py
baseui-1.0.4.dist-info/licenses/LICENSE
baseui-1.0.4.dist-info/METADATA
baseui-1.0.4.dist-info/WHEEL
baseui-1.0.4.dist-info/top_level.txt
baseui-1.0.4.dist-info/RECORD
